alu.v
module alu (
    input clk,
    input [3:0] A,
    input [3:0] B,
    input [2:0] opcode,
    output reg [3:0] result,
    output reg carry,
    output reg zero
);

always @(posedge clk)
begin
    carry = 1'b0;

    case(opcode)

        3'b000:
            {carry, result} = A + B;

        3'b001:
            {carry, result} = A - B;

        3'b010:
            result = A & B;

        3'b011:
            result = A | B;

        3'b100:
            result = A ^ B;

        3'b101:
            result = ~A;

        3'b110:
            result = A << 1;

        3'b111:
            result = A >> 1;

        default:
            result = 4'b0000;

    endcase

    if(result == 4'b0000)
        zero = 1'b1;
    else
        zero = 1'b0;

end

endmodule

alutb.v
`timescale 1ns/1ps

module alu_tb;

    // Inputs
    reg clk;
    reg [3:0] A;
    reg [3:0] B;
    reg [2:0] opcode;

    // Outputs
    wire [3:0] result;
    wire carry;
    wire zero;

    // Instantiate the ALU
    alu uut (
        .clk(clk),
        .A(A),
        .B(B),
        .opcode(opcode),
        .result(result),
        .carry(carry),
        .zero(zero)
    );

    // Clock Generation (10 ns period)
    initial begin
        clk = 0;
        forever #5 clk = ~clk;
    end

    // Test stimulus
    initial begin

        // Generate VCD file
        $dumpfile("alu.vcd");
        $dumpvars(0, alu_tb);

        // Display values on terminal
        $monitor("Time=%0t | Opcode=%b | A=%d | B=%d | Result=%d | Carry=%b | Zero=%b",
                 $time, opcode, A, B, result, carry, zero);

        // Test 1 : Addition
        A = 4'd5;
        B = 4'd3;
        opcode = 3'b000;
        #10;

        // Test 2 : Subtraction
        A = 4'd9;
        B = 4'd2;
        opcode = 3'b001;
        #10;

        // Test 3 : AND
        A = 4'b1100;
        B = 4'b1010;
        opcode = 3'b010;
        #10;

        // Test 4 : OR
        A = 4'b1100;
        B = 4'b1010;
        opcode = 3'b011;
        #10;

        // Test 5 : XOR
        A = 4'b1100;
        B = 4'b1010;
        opcode = 3'b100;
        #10;

        // Test 6 : NOT
        A = 4'b1100;
        B = 4'b0000;
        opcode = 3'b101;
        #10;

        // Test 7 : Left Shift
        A = 4'b0011;
        B = 4'b0000;
        opcode = 3'b110;
        #10;

        // Test 8 : Right Shift
        A = 4'b1000;
        B = 4'b0000;
        opcode = 3'b111;
        #10;

        $finish;
    end

endmodule

alu.vcd
$date
	Wed Jul  8 10:52:17 2026
$end
$version
	Icarus Verilog
$end
$timescale
	1ps
$end
$scope module alu_tb $end
$var wire 1 ! zero $end
$var wire 4 " result [3:0] $end
$var wire 1 # carry $end
$var reg 4 $ A [3:0] $end
$var reg 4 % B [3:0] $end
$var reg 1 & clk $end
$var reg 3 ' opcode [2:0] $end
$scope module uut $end
$var wire 4 ( A [3:0] $end
$var wire 4 ) B [3:0] $end
$var wire 1 & clk $end
$var wire 3 * opcode [2:0] $end
$var reg 1 # carry $end
$var reg 4 + result [3:0] $end
$var reg 1 ! zero $end
$upscope $end
$upscope $end
$enddefinitions $end
$comment Show the parameter values. $end
$dumpall
$end
#0
$dumpvars
bx +
b0 *
b11 )
b101 (
b0 '
0&
b11 %
b101 $
x#
bx "
x!
$end
#5000
0!
b1000 "
b1000 +
0#
1&
#10000
0&
b1 '
b1 *
b10 %
b10 )
b1001 $
b1001 (
#15000
b111 "
b111 +
1&
#20000
0&
b10 '
b10 *
b1010 %
b1010 )
b1100 $
b1100 (
#25000
b1000 "
b1000 +
1&
#30000
0&
b11 '
b11 *
#35000
b1110 "
b1110 +
1&
#40000
0&
b100 '
b100 *
#45000
b110 "
b110 +
1&
#50000
0&
b101 '
b101 *
b0 %
b0 )
#55000
b11 "
b11 +
1&
#60000
0&
b110 '
b110 *
b11 $
b11 (
#65000
b110 "
b110 +
1&
#70000
0&
b111 '
b111 *
b1000 $
b1000 (
#75000
b100 "
b100 +
1&
